ShiningArmor/__init__.py
ShiningArmor/sqliteDB.py
ShiningArmor/twitter.py
ShiningArmor/whatsapp.py
ShiningArmor-1.2.0.dist-info/LICENSE.txt
ShiningArmor-1.2.0.dist-info/METADATA
ShiningArmor-1.2.0.dist-info/WHEEL
ShiningArmor-1.2.0.dist-info/top_level.txt
ShiningArmor-1.2.0.dist-info/RECORD
