Metadata-Version: 2.1
Name: ShiningArmor
Version: 1.2.0
Summary: A collection of python functions for BOTs
Home-page: https://github.com/adabalap/ShiningArmor
Author: Phani Adabala
Author-email: adabala.phani@gmail.com
License: UNKNOWN
Project-URL: Bug Tracker, https://github.com/adabalap/ShiningArmor/issues
Platform: UNKNOWN
Classifier: Programming Language :: Python :: 3
Classifier: License :: OSI Approved :: MIT License
Classifier: Operating System :: OS Independent
Requires-Python: >=3.6
License-File: LICENSE.txt
Requires-Dist: certifi (==2021.5.30)
Requires-Dist: charset-normalizer (==2.0.4)
Requires-Dist: EasyProcess (==0.3)
Requires-Dist: idna (==3.2)
Requires-Dist: oauthlib (==3.1.1)
Requires-Dist: PySocks (==1.7.1)
Requires-Dist: PyVirtualDisplay (==2.2)
Requires-Dist: requests (==2.26.0)
Requires-Dist: requests-oauthlib (==1.3.0)
Requires-Dist: selenium (==3.141.0)
Requires-Dist: six (==1.16.0)
Requires-Dist: tweepy (==3.10.0)
Requires-Dist: urllib3 (==1.26.6)
